depenv/__init__.py
depenv-1.0.1.dist-info/LICENSE
depenv-1.0.1.dist-info/METADATA
depenv-1.0.1.dist-info/WHEEL
depenv-1.0.1.dist-info/top_level.txt
depenv-1.0.1.dist-info/RECORD
