Metadata-Version: 2.1
Name: depenv
Version: 1.0.1
Summary: Inject dependencies via environment variables
Author: Jordan Sanders
Classifier: Development Status :: 3 - Alpha
Classifier: Intended Audience :: Developers
Classifier: License :: OSI Approved :: MIT No Attribution License (MIT-0)
Classifier: Programming Language :: Python :: 3
Classifier: Programming Language :: Python :: 3.10
Classifier: Programming Language :: Python :: 3.11
Classifier: Programming Language :: Python :: 3.7
Classifier: Programming Language :: Python :: 3.8
Classifier: Programming Language :: Python :: 3.9
Classifier: Programming Language :: Python
Classifier: Topic :: Software Development
Requires-Python: >=3.7
License-File: LICENSE
Provides-Extra: dev
Requires-Dist: black ; extra == 'dev'
Requires-Dist: isort ; extra == 'dev'
Requires-Dist: flake8 ; extra == 'dev'
Requires-Dist: pytest ; extra == 'dev'
